ua_banktools/banks/__init__.py
ua_banktools/banks/base.py
ua_banktools/banks/monobank/__init__.py
ua_banktools/banks/monobank/monobank.py
ua_banktools/banks/monobank/types.py
ua_banktools/banks/privatbank/__init__.py
ua_banktools/banks/privatbank/privatbank.py
ua_banktools/banks/privatbank/types.py
ua_banktools/core/__init__.py
ua_banktools/core/ipn.py
ua_banktools-0.1.0.dist-info/LICENSE
ua_banktools-0.1.0.dist-info/METADATA
ua_banktools-0.1.0.dist-info/WHEEL
ua_banktools-0.1.0.dist-info/RECORD
