Metadata-Version: 2.3
Name: ua-banktools
Version: 0.1.0
Summary: 
Author: Anton Shpigunov
Author-email: shpigunov@gmail.com
Requires-Python: >=3.10,<4
Classifier: Programming Language :: Python :: 3
Classifier: Programming Language :: Python :: 3.10
Classifier: Programming Language :: Python :: 3.11
Classifier: Programming Language :: Python :: 3.12
Classifier: Programming Language :: Python :: 3.13
Requires-Dist: pydantic (>=2.1,<3.0)
Requires-Dist: requests (>=2.28.1,<3.0.0)
Requires-Dist: schwifty (>=2022.9.0,<2023.0.0)
